dnslb
