Metadata-Version: 1.1
Name: python-dnslb
Version: 0.2.3
Summary: Simple Python DNS load balancer for geodns
Home-page: http://blogs.mnt.se
Author: Leif Johansson
Author-email: leifj@mnt.se
License: BSD
Keywords: cdn dlb
Platform: UNKNOWN
Requires: threadpool
Requires: pyyaml
